LotinKrillYangiLotin/LotinKrillYangilotin.py
LotinKrillYangiLotin/__init__.py
LotinKrillYangiLotin-1.0.1.dist-info/METADATA
LotinKrillYangiLotin-1.0.1.dist-info/WHEEL
LotinKrillYangiLotin-1.0.1.dist-info/top_level.txt
LotinKrillYangiLotin-1.0.1.dist-info/RECORD
