Metadata-Version: 2.1
Name: LotinKrillYangiLotin
Version: 1.0.1
Summary: Dasturdan o‘zbek tilidagi matnlarni yozuv shaklini almashtirishda va yangi lotin alifbosini joriy qilishda foydalanish mumkin!
Home-page: https://github.com/ddasturbek/LotinKrillYangiLotin
Author: dasturbek
Author-email: sobirovogabek0409@gmail.com
Classifier: Programming Language :: Python :: 3
Classifier: License :: OSI Approved :: MIT License
Classifier: Operating System :: OS Independent
Requires-Python: >=3.6
